argos_trains/__init__.py
argos_trains/callbacks.py
argos_trains/common.py
argos_trains/config.py
argos_trains/logging.py
argos_trains/resume.py
argos_trains/train.py
argos_trains/tune.py
argos_trains/util.py
argos_trains-0.1.0.dist-info/METADATA
argos_trains-0.1.0.dist-info/WHEEL
argos_trains-0.1.0.dist-info/entry_points.txt
argos_trains-0.1.0.dist-info/top_level.txt
argos_trains-0.1.0.dist-info/RECORD
